heroquotes/__init__.py
heroquotes-1.0.dist-info/LICENSE
heroquotes-1.0.dist-info/METADATA
heroquotes-1.0.dist-info/WHEEL
heroquotes-1.0.dist-info/top_level.txt
heroquotes-1.0.dist-info/RECORD
